azureml/__init__.py
azureml/__version__.py
azureml/api/__init__.py
azureml/api/batch/__init__.py
azureml/api/batch/_batch_sdk_utilities.py
azureml/api/batch/batch_handler.py
azureml/api/exceptions/ApiException.py
azureml/api/exceptions/BadRequest.py
azureml/api/exceptions/ClientSideException.py
azureml/api/exceptions/InternalServerError.py
azureml/api/exceptions/NotFound.py
azureml/api/exceptions/ServerSideException.py
azureml/api/exceptions/ServiceUnavailable.py
azureml/api/exceptions/TooManyRequests.py
azureml/api/exceptions/Unauthorized.py
azureml/api/exceptions/UnsupportedMediaType.py
azureml/api/exceptions/__init__.py
azureml/api/realtime/__init__.py
azureml/api/realtime/services.py
azureml/api/realtime/swagger_spec_generator.py
azureml/api/realtime/templates/main_template.txt
azureml/api/realtime/templates/swagger_template.json
azureml/api/schema/__init__.py
azureml/api/schema/baseUtil.py
azureml/api/schema/constants.py
azureml/api/schema/dataTypes.py
azureml/api/schema/numpyUtil.py
azureml/api/schema/pandasUtil.py
azureml/api/schema/pythonUtil.py
azureml/api/schema/sampleDefinition.py
azureml/api/schema/schemaObjects.py
azureml/api/schema/schemaUtil.py
azureml/api/schema/sparkUtil.py
azureml/api/schema/swaggerFromDtype.py
azureml/api/schema/swaggerFromPython.py
azureml/api/schema/swaggerFromSpark.py
azureml/api/schema/utilities.py
azureml/authentication/__init__.py
azureml/authentication/aad_authentication.py
azureml/authentication/ad_authentication.py
azureml/common/__init__.py
azureml/common/configuration.py
azureml/common/http_client.py
azureml/common/utils.py
azureml/deploy/__init__.py
azureml/deploy/deploy_client.py
azureml/deploy/operationalization.py
azureml/deploy/server/__init__.py
azureml/deploy/server/encoding_type.py
azureml/deploy/server/mlserver.py
azureml/deploy/server/mlserver_adapter.py
azureml/deploy/server/service.py
azureml/deploy/server/services.py
azureml_model_management_sdk-1.0.1b6.dist-info/DESCRIPTION.rst
azureml_model_management_sdk-1.0.1b6.dist-info/METADATA
azureml_model_management_sdk-1.0.1b6.dist-info/RECORD
azureml_model_management_sdk-1.0.1b6.dist-info/WHEEL
azureml_model_management_sdk-1.0.1b6.dist-info/metadata.json
azureml_model_management_sdk-1.0.1b6.dist-info/top_level.txt
