Metadata-Version: 2.0
Name: azureml-model-management-sdk
Version: 1.0.1b6
Summary: Microsoft Azure Machine Learning Python SDK for authoring web services
Home-page: https://github.com/Azure/azure-ml-api-sdk-python
Author: Microsoft Corporation
Author-email: deployml@microsoft.com
License: MIT
Keywords: azure,machinelearning,model,operationalization,analytics,mlserver
Platform: UNKNOWN
Classifier: Development Status :: 3 - Alpha
Classifier: Intended Audience :: Developers
Classifier: Intended Audience :: System Administrators
Classifier: License :: OSI Approved :: MIT License
Classifier: Programming Language :: Python
Classifier: Programming Language :: Python :: 2
Classifier: Programming Language :: Python :: 2.7
Classifier: Programming Language :: Python :: 3
Classifier: Programming Language :: Python :: 3.5
Classifier: Topic :: Software Development :: Libraries :: Application Frameworks
Classifier: Topic :: Software Development :: Libraries :: Python Modules
Requires-Dist: adal (>=0.4.5)
Requires-Dist: dill (>=0.2.7.1)
Requires-Dist: liac-arff (>=2.1.1)
Requires-Dist: numpy (>=1.13.0)
Requires-Dist: pandas (>=0.20.2)
Requires-Dist: python-dateutil (>=2.5.3)
Requires-Dist: pytz (>=2017.2)
Requires-Dist: requests (>=2.17.3)
Requires-Dist: six (>=1.10)
